{
  "aggregate": {
    "counters": {
      "vusers.created_by_name.0": 15000,
      "vusers.created": 15000,
      "http.requests": 15000,
      "http.codes.200": 15000,
      "http.responses": 15000,
      "http.downloaded_bytes": 84060000,
      "plugins.metrics-by-endpoint./student/fetch/topics.codes.200": 15000,
      "vusers.failed": 0,
      "vusers.completed": 15000
    },
    "rates": {
      "http.request_rate": 250
    },
    "firstCounterAt": 1749740077109,
    "firstHistogramAt": 1749740077149,
    "lastCounterAt": 1749740137760,
    "lastHistogramAt": 1749740137760,
    "firstMetricAt": 1749740077109,
    "lastMetricAt": 1749740137760,
    "period": 1749740130000,
    "summaries": {
      "http.response_time": {
        "min": 1,
        "max": 410,
        "count": 15000,
        "mean": 31.9,
        "p50": 6,
        "median": 6,
        "p75": 10.1,
        "p90": 59.7,
        "p95": 284.3,
        "p99": 333.7,
        "p999": 399.5
      },
      "http.response_time.2xx": {
        "min": 1,
        "max": 410,
        "count": 15000,
        "mean": 31.9,
        "p50": 6,
        "median": 6,
        "p75": 10.1,
        "p90": 59.7,
        "p95": 284.3,
        "p99": 333.7,
        "p999": 399.5
      },
      "plugins.metrics-by-endpoint.response_time./student/fetch/topics": {
        "min": 1,
        "max": 410,
        "count": 15000,
        "mean": 31.9,
        "p50": 6,
        "median": 6,
        "p75": 10.1,
        "p90": 59.7,
        "p95": 284.3,
        "p99": 333.7,
        "p999": 399.5
      },
      "vusers.session_length": {
        "min": 3.6,
        "max": 411.3,
        "count": 15000,
        "mean": 33.5,
        "p50": 7.9,
        "median": 7.9,
        "p75": 12.1,
        "p90": 61,
        "p95": 284.3,
        "p99": 340.4,
        "p999": 399.5
      }
    },
    "histograms": {
      "http.response_time": {
        "min": 1,
        "max": 410,
        "count": 15000,
        "mean": 31.9,
        "p50": 6,
        "median": 6,
        "p75": 10.1,
        "p90": 59.7,
        "p95": 284.3,
        "p99": 333.7,
        "p999": 399.5
      },
      "http.response_time.2xx": {
        "min": 1,
        "max": 410,
        "count": 15000,
        "mean": 31.9,
        "p50": 6,
        "median": 6,
        "p75": 10.1,
        "p90": 59.7,
        "p95": 284.3,
        "p99": 333.7,
        "p999": 399.5
      },
      "plugins.metrics-by-endpoint.response_time./student/fetch/topics": {
        "min": 1,
        "max": 410,
        "count": 15000,
        "mean": 31.9,
        "p50": 6,
        "median": 6,
        "p75": 10.1,
        "p90": 59.7,
        "p95": 284.3,
        "p99": 333.7,
        "p999": 399.5
      },
      "vusers.session_length": {
        "min": 3.6,
        "max": 411.3,
        "count": 15000,
        "mean": 33.5,
        "p50": 7.9,
        "median": 7.9,
        "p75": 12.1,
        "p90": 61,
        "p95": 284.3,
        "p99": 340.4,
        "p999": 399.5
      }
    }
  },
  "intermediate": [
    {
      "counters": {
        "vusers.created_by_name.0": 644,
        "vusers.created": 644,
        "http.requests": 644,
        "http.codes.200": 575,
        "http.responses": 575,
        "http.downloaded_bytes": 3222300,
        "plugins.metrics-by-endpoint./student/fetch/topics.codes.200": 575,
        "vusers.failed": 0,
        "vusers.completed": 575
      },
      "rates": {
        "http.request_rate": 258
      },
      "http.request_rate": null,
      "firstCounterAt": 1749740077109,
      "firstHistogramAt": 1749740077149,
      "lastCounterAt": 1749740079999,
      "lastHistogramAt": 1749740079996,
      "firstMetricAt": 1749740077109,
      "lastMetricAt": 1749740079999,
      "period": "1749740070000",
      "summaries": {
        "http.response_time": {
          "min": 4,
          "max": 352,
          "count": 575,
          "mean": 269.2,
          "p50": 301.9,
          "median": 301.9,
          "p75": 314.2,
          "p90": 333.7,
          "p95": 333.7,
          "p99": 340.4,
          "p999": 347.3
        },
        "http.response_time.2xx": {
          "min": 4,
          "max": 352,
          "count": 575,
          "mean": 269.2,
          "p50": 301.9,
          "median": 301.9,
          "p75": 314.2,
          "p90": 333.7,
          "p95": 333.7,
          "p99": 340.4,
          "p999": 347.3
        },
        "plugins.metrics-by-endpoint.response_time./student/fetch/topics": {
          "min": 4,
          "max": 352,
          "count": 575,
          "mean": 269.2,
          "p50": 301.9,
          "median": 301.9,
          "p75": 314.2,
          "p90": 333.7,
          "p95": 333.7,
          "p99": 340.4,
          "p999": 347.3
        },
        "vusers.session_length": {
          "min": 6.4,
          "max": 358.7,
          "count": 575,
          "mean": 272.7,
          "p50": 308,
          "median": 308,
          "p75": 320.6,
          "p90": 333.7,
          "p95": 340.4,
          "p99": 347.3,
          "p999": 354.3
        }
      },
      "histograms": {
        "http.response_time": {
          "min": 4,
          "max": 352,
          "count": 575,
          "mean": 269.2,
          "p50": 301.9,
          "median": 301.9,
          "p75": 314.2,
          "p90": 333.7,
          "p95": 333.7,
          "p99": 340.4,
          "p999": 347.3
        },
        "http.response_time.2xx": {
          "min": 4,
          "max": 352,
          "count": 575,
          "mean": 269.2,
          "p50": 301.9,
          "median": 301.9,
          "p75": 314.2,
          "p90": 333.7,
          "p95": 333.7,
          "p99": 340.4,
          "p999": 347.3
        },
        "plugins.metrics-by-endpoint.response_time./student/fetch/topics": {
          "min": 4,
          "max": 352,
          "count": 575,
          "mean": 269.2,
          "p50": 301.9,
          "median": 301.9,
          "p75": 314.2,
          "p90": 333.7,
          "p95": 333.7,
          "p99": 340.4,
          "p999": 347.3
        },
        "vusers.session_length": {
          "min": 6.4,
          "max": 358.7,
          "count": 575,
          "mean": 272.7,
          "p50": 308,
          "median": 308,
          "p75": 320.6,
          "p90": 333.7,
          "p95": 340.4,
          "p99": 347.3,
          "p999": 354.3
        }
      }
    },
    {
      "counters": {
        "http.codes.200": 2567,
        "http.responses": 2567,
        "http.downloaded_bytes": 14385468,
        "plugins.metrics-by-endpoint./student/fetch/topics.codes.200": 2567,
        "vusers.failed": 0,
        "vusers.completed": 2567,
        "vusers.created_by_name.0": 2500,
        "vusers.created": 2500,
        "http.requests": 2500
      },
      "rates": {
        "http.request_rate": 250
      },
      "http.request_rate": null,
      "firstCounterAt": 1749740080003,
      "firstHistogramAt": 1749740080003,
      "lastCounterAt": 1749740089999,
      "lastHistogramAt": 1749740089999,
      "firstMetricAt": 1749740080003,
      "lastMetricAt": 1749740089999,
      "period": "1749740080000",
      "summaries": {
        "http.response_time": {
          "min": 2,
          "max": 345,
          "count": 2567,
          "mean": 60.4,
          "p50": 7.9,
          "median": 7.9,
          "p75": 61,
          "p90": 252.2,
          "p95": 301.9,
          "p99": 333.7,
          "p999": 340.4
        },
        "http.response_time.2xx": {
          "min": 2,
          "max": 345,
          "count": 2567,
          "mean": 60.4,
          "p50": 7.9,
          "median": 7.9,
          "p75": 61,
          "p90": 252.2,
          "p95": 301.9,
          "p99": 333.7,
          "p999": 340.4
        },
        "plugins.metrics-by-endpoint.response_time./student/fetch/topics": {
          "min": 2,
          "max": 345,
          "count": 2567,
          "mean": 60.4,
          "p50": 7.9,
          "median": 7.9,
          "p75": 61,
          "p90": 252.2,
          "p95": 301.9,
          "p99": 333.7,
          "p999": 340.4
        },
        "vusers.session_length": {
          "min": 3.8,
          "max": 345.6,
          "count": 2567,
          "mean": 62.3,
          "p50": 9.9,
          "median": 9.9,
          "p75": 62.2,
          "p90": 252.2,
          "p95": 308,
          "p99": 333.7,
          "p999": 347.3
        }
      },
      "histograms": {
        "http.response_time": {
          "min": 2,
          "max": 345,
          "count": 2567,
          "mean": 60.4,
          "p50": 7.9,
          "median": 7.9,
          "p75": 61,
          "p90": 252.2,
          "p95": 301.9,
          "p99": 333.7,
          "p999": 340.4
        },
        "http.response_time.2xx": {
          "min": 2,
          "max": 345,
          "count": 2567,
          "mean": 60.4,
          "p50": 7.9,
          "median": 7.9,
          "p75": 61,
          "p90": 252.2,
          "p95": 301.9,
          "p99": 333.7,
          "p999": 340.4
        },
        "plugins.metrics-by-endpoint.response_time./student/fetch/topics": {
          "min": 2,
          "max": 345,
          "count": 2567,
          "mean": 60.4,
          "p50": 7.9,
          "median": 7.9,
          "p75": 61,
          "p90": 252.2,
          "p95": 301.9,
          "p99": 333.7,
          "p999": 340.4
        },
        "vusers.session_length": {
          "min": 3.8,
          "max": 345.6,
          "count": 2567,
          "mean": 62.3,
          "p50": 9.9,
          "median": 9.9,
          "p75": 62.2,
          "p90": 252.2,
          "p95": 308,
          "p99": 333.7,
          "p999": 347.3
        }
      }
    },
    {
      "counters": {
        "http.codes.200": 2446,
        "http.responses": 2446,
        "http.downloaded_bytes": 13707384,
        "plugins.metrics-by-endpoint./student/fetch/topics.codes.200": 2446,
        "vusers.failed": 0,
        "vusers.completed": 2446,
        "vusers.created_by_name.0": 2500,
        "vusers.created": 2500,
        "http.requests": 2500
      },
      "rates": {
        "http.request_rate": 250
      },
      "http.request_rate": null,
      "firstCounterAt": 1749740090001,
      "firstHistogramAt": 1749740090001,
      "lastCounterAt": 1749740099999,
      "lastHistogramAt": 1749740099999,
      "firstMetricAt": 1749740090001,
      "lastMetricAt": 1749740099999,
      "period": "1749740090000",
      "summaries": {
        "http.response_time": {
          "min": 2,
          "max": 410,
          "count": 2446,
          "mean": 31.8,
          "p50": 7,
          "median": 7,
          "p75": 10.1,
          "p90": 26.8,
          "p95": 284.3,
          "p99": 391.6,
          "p999": 407.5
        },
        "http.response_time.2xx": {
          "min": 2,
          "max": 410,
          "count": 2446,
          "mean": 31.8,
          "p50": 7,
          "median": 7,
          "p75": 10.1,
          "p90": 26.8,
          "p95": 284.3,
          "p99": 391.6,
          "p999": 407.5
        },
        "plugins.metrics-by-endpoint.response_time./student/fetch/topics": {
          "min": 2,
          "max": 410,
          "count": 2446,
          "mean": 31.8,
          "p50": 7,
          "median": 7,
          "p75": 10.1,
          "p90": 26.8,
          "p95": 284.3,
          "p99": 391.6,
          "p999": 407.5
        },
        "vusers.session_length": {
          "min": 3.8,
          "max": 411.3,
          "count": 2446,
          "mean": 33.4,
          "p50": 8.2,
          "median": 8.2,
          "p75": 11.8,
          "p90": 29.7,
          "p95": 284.3,
          "p99": 391.6,
          "p999": 407.5
        }
      },
      "histograms": {
        "http.response_time": {
          "min": 2,
          "max": 410,
          "count": 2446,
          "mean": 31.8,
          "p50": 7,
          "median": 7,
          "p75": 10.1,
          "p90": 26.8,
          "p95": 284.3,
          "p99": 391.6,
          "p999": 407.5
        },
        "http.response_time.2xx": {
          "min": 2,
          "max": 410,
          "count": 2446,
          "mean": 31.8,
          "p50": 7,
          "median": 7,
          "p75": 10.1,
          "p90": 26.8,
          "p95": 284.3,
          "p99": 391.6,
          "p999": 407.5
        },
        "plugins.metrics-by-endpoint.response_time./student/fetch/topics": {
          "min": 2,
          "max": 410,
          "count": 2446,
          "mean": 31.8,
          "p50": 7,
          "median": 7,
          "p75": 10.1,
          "p90": 26.8,
          "p95": 284.3,
          "p99": 391.6,
          "p999": 407.5
        },
        "vusers.session_length": {
          "min": 3.8,
          "max": 411.3,
          "count": 2446,
          "mean": 33.4,
          "p50": 8.2,
          "median": 8.2,
          "p75": 11.8,
          "p90": 29.7,
          "p95": 284.3,
          "p99": 391.6,
          "p999": 407.5
        }
      }
    },
    {
      "counters": {
        "http.codes.200": 2555,
        "http.responses": 2555,
        "http.downloaded_bytes": 14318220,
        "plugins.metrics-by-endpoint./student/fetch/topics.codes.200": 2555,
        "vusers.failed": 0,
        "vusers.completed": 2555,
        "vusers.created_by_name.0": 2500,
        "vusers.created": 2500,
        "http.requests": 2500
      },
      "rates": {
        "http.request_rate": 250
      },
      "http.request_rate": null,
      "firstCounterAt": 1749740100002,
      "firstHistogramAt": 1749740100002,
      "lastCounterAt": 1749740109998,
      "lastHistogramAt": 1749740109998,
      "firstMetricAt": 1749740100002,
      "lastMetricAt": 1749740109998,
      "period": "1749740100000",
      "summaries": {
        "http.response_time": {
          "min": 1,
          "max": 225,
          "count": 2555,
          "mean": 18.1,
          "p50": 7,
          "median": 7,
          "p75": 10.9,
          "p90": 19.1,
          "p95": 111.1,
          "p99": 214.9,
          "p999": 223.7
        },
        "http.response_time.2xx": {
          "min": 1,
          "max": 225,
          "count": 2555,
          "mean": 18.1,
          "p50": 7,
          "median": 7,
          "p75": 10.9,
          "p90": 19.1,
          "p95": 111.1,
          "p99": 214.9,
          "p999": 223.7
        },
        "plugins.metrics-by-endpoint.response_time./student/fetch/topics": {
          "min": 1,
          "max": 225,
          "count": 2555,
          "mean": 18.1,
          "p50": 7,
          "median": 7,
          "p75": 10.9,
          "p90": 19.1,
          "p95": 111.1,
          "p99": 214.9,
          "p999": 223.7
        },
        "vusers.session_length": {
          "min": 3.6,
          "max": 226.7,
          "count": 2555,
          "mean": 19.8,
          "p50": 8.9,
          "median": 8.9,
          "p75": 13.1,
          "p90": 21.5,
          "p95": 111.1,
          "p99": 214.9,
          "p999": 223.7
        }
      },
      "histograms": {
        "http.response_time": {
          "min": 1,
          "max": 225,
          "count": 2555,
          "mean": 18.1,
          "p50": 7,
          "median": 7,
          "p75": 10.9,
          "p90": 19.1,
          "p95": 111.1,
          "p99": 214.9,
          "p999": 223.7
        },
        "http.response_time.2xx": {
          "min": 1,
          "max": 225,
          "count": 2555,
          "mean": 18.1,
          "p50": 7,
          "median": 7,
          "p75": 10.9,
          "p90": 19.1,
          "p95": 111.1,
          "p99": 214.9,
          "p999": 223.7
        },
        "plugins.metrics-by-endpoint.response_time./student/fetch/topics": {
          "min": 1,
          "max": 225,
          "count": 2555,
          "mean": 18.1,
          "p50": 7,
          "median": 7,
          "p75": 10.9,
          "p90": 19.1,
          "p95": 111.1,
          "p99": 214.9,
          "p999": 223.7
        },
        "vusers.session_length": {
          "min": 3.6,
          "max": 226.7,
          "count": 2555,
          "mean": 19.8,
          "p50": 8.9,
          "median": 8.9,
          "p75": 13.1,
          "p90": 21.5,
          "p95": 111.1,
          "p99": 214.9,
          "p999": 223.7
        }
      }
    },
    {
      "counters": {
        "vusers.created_by_name.0": 2500,
        "vusers.created": 2500,
        "http.requests": 2500,
        "http.codes.200": 2500,
        "http.responses": 2500,
        "http.downloaded_bytes": 14010000,
        "plugins.metrics-by-endpoint./student/fetch/topics.codes.200": 2500,
        "vusers.failed": 0,
        "vusers.completed": 2500
      },
      "rates": {
        "http.request_rate": 250
      },
      "http.request_rate": null,
      "firstCounterAt": 1749740110002,
      "firstHistogramAt": 1749740110002,
      "lastCounterAt": 1749740119998,
      "lastHistogramAt": 1749740119998,
      "firstMetricAt": 1749740110002,
      "lastMetricAt": 1749740119998,
      "period": "1749740110000",
      "summaries": {
        "http.response_time": {
          "min": 2,
          "max": 26,
          "count": 2500,
          "mean": 6.5,
          "p50": 6,
          "median": 6,
          "p75": 7.9,
          "p90": 10.9,
          "p95": 13.1,
          "p99": 18,
          "p999": 21.1
        },
        "http.response_time.2xx": {
          "min": 2,
          "max": 26,
          "count": 2500,
          "mean": 6.5,
          "p50": 6,
          "median": 6,
          "p75": 7.9,
          "p90": 10.9,
          "p95": 13.1,
          "p99": 18,
          "p999": 21.1
        },
        "plugins.metrics-by-endpoint.response_time./student/fetch/topics": {
          "min": 2,
          "max": 26,
          "count": 2500,
          "mean": 6.5,
          "p50": 6,
          "median": 6,
          "p75": 7.9,
          "p90": 10.9,
          "p95": 13.1,
          "p99": 18,
          "p999": 21.1
        },
        "vusers.session_length": {
          "min": 3.6,
          "max": 27.8,
          "count": 2500,
          "mean": 7.9,
          "p50": 6.9,
          "median": 6.9,
          "p75": 9.3,
          "p90": 12.3,
          "p95": 14.4,
          "p99": 19.5,
          "p999": 22.9
        }
      },
      "histograms": {
        "http.response_time": {
          "min": 2,
          "max": 26,
          "count": 2500,
          "mean": 6.5,
          "p50": 6,
          "median": 6,
          "p75": 7.9,
          "p90": 10.9,
          "p95": 13.1,
          "p99": 18,
          "p999": 21.1
        },
        "http.response_time.2xx": {
          "min": 2,
          "max": 26,
          "count": 2500,
          "mean": 6.5,
          "p50": 6,
          "median": 6,
          "p75": 7.9,
          "p90": 10.9,
          "p95": 13.1,
          "p99": 18,
          "p999": 21.1
        },
        "plugins.metrics-by-endpoint.response_time./student/fetch/topics": {
          "min": 2,
          "max": 26,
          "count": 2500,
          "mean": 6.5,
          "p50": 6,
          "median": 6,
          "p75": 7.9,
          "p90": 10.9,
          "p95": 13.1,
          "p99": 18,
          "p999": 21.1
        },
        "vusers.session_length": {
          "min": 3.6,
          "max": 27.8,
          "count": 2500,
          "mean": 7.9,
          "p50": 6.9,
          "median": 6.9,
          "p75": 9.3,
          "p90": 12.3,
          "p95": 14.4,
          "p99": 19.5,
          "p999": 22.9
        }
      }
    },
    {
      "counters": {
        "vusers.created_by_name.0": 2500,
        "vusers.created": 2500,
        "http.requests": 2500,
        "http.codes.200": 2497,
        "http.responses": 2497,
        "http.downloaded_bytes": 13993188,
        "plugins.metrics-by-endpoint./student/fetch/topics.codes.200": 2497,
        "vusers.failed": 0,
        "vusers.completed": 2497
      },
      "rates": {
        "http.request_rate": 250
      },
      "http.request_rate": null,
      "firstCounterAt": 1749740120002,
      "firstHistogramAt": 1749740120002,
      "lastCounterAt": 1749740129998,
      "lastHistogramAt": 1749740129995,
      "firstMetricAt": 1749740120002,
      "lastMetricAt": 1749740129998,
      "period": "1749740120000",
      "summaries": {
        "http.response_time": {
          "min": 2,
          "max": 20,
          "count": 2497,
          "mean": 6.5,
          "p50": 6,
          "median": 6,
          "p75": 7.9,
          "p90": 10.9,
          "p95": 13.1,
          "p99": 16.9,
          "p999": 19.1
        },
        "http.response_time.2xx": {
          "min": 2,
          "max": 20,
          "count": 2497,
          "mean": 6.5,
          "p50": 6,
          "median": 6,
          "p75": 7.9,
          "p90": 10.9,
          "p95": 13.1,
          "p99": 16.9,
          "p999": 19.1
        },
        "plugins.metrics-by-endpoint.response_time./student/fetch/topics": {
          "min": 2,
          "max": 20,
          "count": 2497,
          "mean": 6.5,
          "p50": 6,
          "median": 6,
          "p75": 7.9,
          "p90": 10.9,
          "p95": 13.1,
          "p99": 16.9,
          "p999": 19.1
        },
        "vusers.session_length": {
          "min": 3.6,
          "max": 26.3,
          "count": 2497,
          "mean": 7.9,
          "p50": 7,
          "median": 7,
          "p75": 9.3,
          "p90": 12.6,
          "p95": 14.7,
          "p99": 18.4,
          "p999": 21.1
        }
      },
      "histograms": {
        "http.response_time": {
          "min": 2,
          "max": 20,
          "count": 2497,
          "mean": 6.5,
          "p50": 6,
          "median": 6,
          "p75": 7.9,
          "p90": 10.9,
          "p95": 13.1,
          "p99": 16.9,
          "p999": 19.1
        },
        "http.response_time.2xx": {
          "min": 2,
          "max": 20,
          "count": 2497,
          "mean": 6.5,
          "p50": 6,
          "median": 6,
          "p75": 7.9,
          "p90": 10.9,
          "p95": 13.1,
          "p99": 16.9,
          "p999": 19.1
        },
        "plugins.metrics-by-endpoint.response_time./student/fetch/topics": {
          "min": 2,
          "max": 20,
          "count": 2497,
          "mean": 6.5,
          "p50": 6,
          "median": 6,
          "p75": 7.9,
          "p90": 10.9,
          "p95": 13.1,
          "p99": 16.9,
          "p999": 19.1
        },
        "vusers.session_length": {
          "min": 3.6,
          "max": 26.3,
          "count": 2497,
          "mean": 7.9,
          "p50": 7,
          "median": 7,
          "p75": 9.3,
          "p90": 12.6,
          "p95": 14.7,
          "p99": 18.4,
          "p999": 21.1
        }
      }
    },
    {
      "counters": {
        "http.codes.200": 1860,
        "http.responses": 1860,
        "http.downloaded_bytes": 10423440,
        "plugins.metrics-by-endpoint./student/fetch/topics.codes.200": 1860,
        "vusers.failed": 0,
        "vusers.completed": 1860,
        "vusers.created_by_name.0": 1856,
        "vusers.created": 1856,
        "http.requests": 1856
      },
      "rates": {
        "http.request_rate": 250
      },
      "http.request_rate": null,
      "firstCounterAt": 1749740130004,
      "firstHistogramAt": 1749740130006,
      "lastCounterAt": 1749740137760,
      "lastHistogramAt": 1749740137760,
      "firstMetricAt": 1749740130004,
      "lastMetricAt": 1749740137760,
      "period": "1749740130000",
      "summaries": {
        "http.response_time": {
          "min": 1,
          "max": 31,
          "count": 1860,
          "mean": 6.5,
          "p50": 5,
          "median": 5,
          "p75": 7,
          "p90": 10.1,
          "p95": 13.1,
          "p99": 24.8,
          "p999": 30.3
        },
        "http.response_time.2xx": {
          "min": 1,
          "max": 31,
          "count": 1860,
          "mean": 6.5,
          "p50": 5,
          "median": 5,
          "p75": 7,
          "p90": 10.1,
          "p95": 13.1,
          "p99": 24.8,
          "p999": 30.3
        },
        "plugins.metrics-by-endpoint.response_time./student/fetch/topics": {
          "min": 1,
          "max": 31,
          "count": 1860,
          "mean": 6.5,
          "p50": 5,
          "median": 5,
          "p75": 7,
          "p90": 10.1,
          "p95": 13.1,
          "p99": 24.8,
          "p999": 30.3
        },
        "vusers.session_length": {
          "min": 3.6,
          "max": 33.3,
          "count": 1860,
          "mean": 7.9,
          "p50": 6.6,
          "median": 6.6,
          "p75": 8.9,
          "p90": 12.3,
          "p95": 14.4,
          "p99": 26.8,
          "p999": 32.8
        }
      },
      "histograms": {
        "http.response_time": {
          "min": 1,
          "max": 31,
          "count": 1860,
          "mean": 6.5,
          "p50": 5,
          "median": 5,
          "p75": 7,
          "p90": 10.1,
          "p95": 13.1,
          "p99": 24.8,
          "p999": 30.3
        },
        "http.response_time.2xx": {
          "min": 1,
          "max": 31,
          "count": 1860,
          "mean": 6.5,
          "p50": 5,
          "median": 5,
          "p75": 7,
          "p90": 10.1,
          "p95": 13.1,
          "p99": 24.8,
          "p999": 30.3
        },
        "plugins.metrics-by-endpoint.response_time./student/fetch/topics": {
          "min": 1,
          "max": 31,
          "count": 1860,
          "mean": 6.5,
          "p50": 5,
          "median": 5,
          "p75": 7,
          "p90": 10.1,
          "p95": 13.1,
          "p99": 24.8,
          "p999": 30.3
        },
        "vusers.session_length": {
          "min": 3.6,
          "max": 33.3,
          "count": 1860,
          "mean": 7.9,
          "p50": 6.6,
          "median": 6.6,
          "p75": 8.9,
          "p90": 12.3,
          "p95": 14.4,
          "p99": 26.8,
          "p999": 32.8
        }
      }
    }
  ]
}